[
  {
    "Base info": {
      "Application name": "launcher.exe",
      "Dump date": "Mon Jan 05 20:25:14 2026",
      "Dump tick count": 41398786,
      "Graphics API": "Vulkan",
      "PID": 57920
    }
  },
  {
    "Display driver info": {
      "Version": "581.80"
    }
  },
  {
    "OS info": {
      "Build number": 26200,
      "Service pack major version": 0,
      "Service pack minor version": 0,
      "Windows major version": 10,
      "Windows minor version": 0,
      "Windows product type": 1
    }
  },
  {
    "GPU info": {
      "Adapter LUID": 96254,
      "Adapter name": "GB203-A"
    }
  },
  {
    "Page fault info": {
      "Access Type": "Unknown",
      "Client": "Unknown",
      "Engine": "Unknown",
      "Fault Type": "The MMU returned an unknown reason.",
      "GPU virtual address": 17554087936
    }
  },
  {
    "Device info": {
      "Adapter reset occurred": false,
      "Device state": "Error_DMA_PageFault",
      "Engine reset occurred": true
    }
  },
  {
    "Aftermath markers": {
      "Context": {
        "Events": [
          {
            "Event": {
              "Callstack": {
                "Stack": [
                  {
                    "Entry": {
                      "Module name": "nvoglv64.dll",
                      "Pointer": 140723177725031
                    }
                  },
                  {
                    "Entry": {
                      "Module name": "nvoglv64.dll",
                      "Pointer": 140723178817231
                    }
                  },
                  {
                    "Entry": {
                      "Module name": "VkLayer_khronos_validation.dll",
                      "Pointer": 140722826990536
                    }
                  },
                  {
                    "Entry": {
                      "Module name": "vulkan-1.dll",
                      "Pointer": 140723117774867
                    }
                  },
                  {
                    "Entry": {
                      "Module name": "Launcher.exe",
                      "Pointer": 140701736287122
                    }
                  },
                  {
                    "Entry": {
                      "Module name": "Launcher.exe",
                      "Pointer": 140701736284846
                    }
                  },
                  {
                    "Entry": {
                      "Module name": "Launcher.exe",
                      "Pointer": 140701736286440
                    }
                  },
                  {
                    "Entry": {
                      "Module name": "Launcher.exe",
                      "Pointer": 140701736184480
                    }
                  },
                  {
                    "Entry": {
                      "Module name": "Launcher.exe",
                      "Pointer": 140701736421925
                    }
                  },
                  {
                    "Entry": {
                      "Module name": "Launcher.exe",
                      "Pointer": 140701734727637
                    }
                  },
                  {
                    "Entry": {
                      "Module name": "Launcher.exe",
                      "Pointer": 140701734737840
                    }
                  },
                  {
                    "Entry": {
                      "Module name": "Launcher.exe",
                      "Pointer": 140701734669766
                    }
                  },
                  {
                    "Entry": {
                      "Module name": "Launcher.exe",
                      "Pointer": 140701734466691
                    }
                  },
                  {
                    "Entry": {
                      "Module name": "Launcher.exe",
                      "Pointer": 140701738829897
                    }
                  },
                  {
                    "Entry": {
                      "Module name": "Launcher.exe",
                      "Pointer": 140701738829614
                    }
                  },
                  {
                    "Entry": {
                      "Module name": "Launcher.exe",
                      "Pointer": 140701738829294
                    }
                  }
                ]
              },
              "Pipe": "Unknown",
              "Status": "NotStarted",
              "Type": "Automatic"
            }
          },
          {
            "Event": {
              "Callstack": {
                "Stack": [
                  {
                    "Entry": {
                      "Module name": "nvoglv64.dll",
                      "Pointer": 140723177725031
                    }
                  },
                  {
                    "Entry": {
                      "Module name": "nvoglv64.dll",
                      "Pointer": 140723178814988
                    }
                  },
                  {
                    "Entry": {
                      "Module name": "nvoglv64.dll",
                      "Pointer": 140723178098873
                    }
                  },
                  {
                    "Entry": {
                      "Module name": "VkLayer_khronos_validation.dll",
                      "Pointer": 140722826941868
                    }
                  },
                  {
                    "Entry": {
                      "Module name": "vulkan-1.dll",
                      "Pointer": 140723117773213
                    }
                  },
                  {
                    "Entry": {
                      "Module name": "Launcher.exe",
                      "Pointer": 140701735015771
                    }
                  },
                  {
                    "Entry": {
                      "Module name": "Launcher.exe",
                      "Pointer": 140701735012032
                    }
                  },
                  {
                    "Entry": {
                      "Module name": "Launcher.exe",
                      "Pointer": 140701736310039
                    }
                  },
                  {
                    "Entry": {
                      "Module name": "Launcher.exe",
                      "Pointer": 140701734709893
                    }
                  },
                  {
                    "Entry": {
                      "Module name": "Launcher.exe",
                      "Pointer": 140701734694471
                    }
                  },
                  {
                    "Entry": {
                      "Module name": "Launcher.exe",
                      "Pointer": 140701734740846
                    }
                  },
                  {
                    "Entry": {
                      "Module name": "Launcher.exe",
                      "Pointer": 140701734711727
                    }
                  },
                  {
                    "Entry": {
                      "Module name": "Launcher.exe",
                      "Pointer": 140701734711282
                    }
                  },
                  {
                    "Entry": {
                      "Module name": "Launcher.exe",
                      "Pointer": 140701731355672
                    }
                  },
                  {
                    "Entry": {
                      "Module name": "Launcher.exe",
                      "Pointer": 140701731084796
                    }
                  },
                  {
                    "Entry": {
                      "Module name": "Launcher.exe",
                      "Pointer": 140701732150727
                    }
                  }
                ]
              },
              "Pipe": "Unknown",
              "Status": "Finished",
              "Type": "Automatic"
            }
          }
        ],
        "Type": "CommandQueue"
      }
    }
  },
  {
    "Shader infos": {
      "Info": {
        "Shader hash": 5311637900166545731,
        "Shader name": "compute_02",
        "Shader size": 3072,
        "Shader type": "Compute"
      }
    }
  },
  {
    "ApplicationName": "VkHelloNsightAftermath"
  },
  {
    "ApplicationVersion": "v1.0"
  },
  {
    "UserDefined+0": "This is a GPU crash dump example."
  },
  {
    "UserDefined+1": "Engine State: Rendering."
  },
  {
    "UserDefined+2": "More user-defined information..."
  },
  {
    "Fingerprint": {
      "Hash": 17319188383084551331,
      "Quality": 0
    }
  }
]